{
  "total": 1003,
  "items": [
      {
          "eyes": "brown",
          "sex": "Male",
          "age_max": null,
          "url": "https://www.fbi.gov/wanted/cei/noel-romero-herrera",
          "ncic": "W761297178",
          "path": "/wanted/cei/noel-romero-herrera",
          "locations": null,
          "weight_min": 190,
          "place_of_birth": "Colorado",
          "reward_min": 0,
          "subjects": [
              "Criminal Enterprise Investigations"
          ],
          "additional_information": null,
          "reward_max": 0,
          "languages": null,
          "uid": "c11e9d4ef96541d1898de58158c5753e",
          "eyes_raw": "Brown",
          "height_max": 69,
          "nationality": null,
          "age_range": null,
          "height_min": 68,
          "aliases": [
              "\"Joker\"",
              "Noal Romero Herrera",
              "Noel Herrera",
              "Noel R. Herrera",
              "Noel Romero",
              "Noel Romero-Herrera"
          ],
          "reward_text": "The FBI is offering a reward of up to $10,000 for information leading to the arrest of Noel Romero Herrera.",
          "possible_countries": null,
          "description": "Conspiracy to Possess Cocaine with Intent to Distribute; Possession with Intent to Distribute Cocaine and Distribution of Cocaine; Aiding and Abetting",
          "caution": "<p>Noel Romero Herrera is wanted for his alleged involvement in a drug-trafficking organization that operated in Montana from approximately 2007 to approximately September of 2010.</p>\r\n<p> </p>\r\n<p>On February 17, 2011, a federal arrest warrant was issued by the United States District Court, District of Montana, Great Falls Division, Billings, Montana, after Herrera was charged federally with conspiracy to possess cocaine with intent to distribute, possession with intent to distribute cocaine and distribution of cocaine, and aiding and abetting.</p>",
          "weight_max": 200,
          "legat_names": null,
          "race": "hispanic",
          "modified": "2020-01-09T12:40:37+00:00",
          "publication": "2018-01-26T13:30:00",
          "weight": "190 to 200 pounds",
          "status": "na",
          "possible_states": null,
          "scars_and_marks": "Herrera has tattoos on his head, back, chest, left arm, neck, and right arm. He has skin discoloration on his neck.",
          "images": [
              {
                  "thumb": "https://www.fbi.gov/wanted/cei/noel-romero-herrera/@@images/image/thumb",
                  "original": "https://www.fbi.gov/wanted/cei/noel-romero-herrera/@@images/image",
                  "caption": "Photograph taken in 2010",
                  "large": "https://www.fbi.gov/wanted/cei/noel-romero-herrera/@@images/image/large"
              }
          ],
          "remarks": "<p>Herrera has previously lived in Murray, Midvale, Sandy, and Salt Lake City, Utah.</p>",
          "files": [
              {
                  "name": "English",
                  "url": "https://www.fbi.gov/wanted/cei/noel-romero-herrera/download.pdf"
              }
          ],
          "field_offices": [
              "saltlakecity"
          ],
          "coordinates": [],
          "race_raw": "White (Hispanic)",
          "hair_raw": "Black",
          "complexion": null,
          "build": null,
          "person_classification": "Main",
          "dates_of_birth_used": [
              "June 30, 1982"
          ],
          "details": null,
          "warning_message": "SHOULD BE CONSIDERED ARMED AND DANGEROUS",
          "suspects": null,
          "age_min": null,
          "hair": "black",
          "title": "NOEL ROMERO HERRERA",
          "occupations": null,
          "@id": "https://api.fbi.gov/@wanted-person/c11e9d4ef96541d1898de58158c5753e"
      },
      {
          "dates_of_birth_used": null,
          "images": [
              {
                  "caption": null,
                  "large": "https://www.fbi.gov/wanted/vicap/homicides-and-sexual-assaults/unidentified-individual---albuquerque-new-mexico/@@images/image/large",
                  "thumb": "https://www.fbi.gov/wanted/vicap/homicides-and-sexual-assaults/unidentified-individual---albuquerque-new-mexico/@@images/image/thumb",
                  "original": "https://www.fbi.gov/wanted/vicap/homicides-and-sexual-assaults/unidentified-individual---albuquerque-new-mexico/@@images/image"
              }
          ],
          "details": "<p>On May 1, 2019, an unknown individual approached the victim at an art exhibit and interjected himself into her social circle. None of the victim's friends could recall having seen this individual before. The individual followed the victim and her friends to various bars and restaurants throughout the night, sharing only a limited amount of information about himself. The picture above was taken at the Canvass Artistry bar on Central Avenue in Albuquerque, New Mexico.</p>\r\n<p> </p>\r\n<p>At the end of the evening , the suspect appeared to be intoxicated and asked the victim for a ride to a TA truck stop, where he advised his \"rig\" was parked. At the truck stop, the suspect became forceful and sexually assaulted the victim in her vehicle.</p>\r\n<p> </p>\r\n<p>Witnesses advised the suspect spoke with an accent, possibly Haitian or Dominican. He advised several people that he drives trucks for a living, and was only passing through Albuquerque on his way to California. He also mentioned that he was based out of Denver, Colorado, but did not mention what company he worked for.</p>",
          "warning_message": null,
          "build": null,
          "person_classification": "Main",
          "complexion": null,
          "race": "black",
          "occupations": null,
          "suspects": null,
          "age_min": 30,
          "hair": "black",
          "legat_names": null,
          "modified": "2020-01-06T16:07:53+00:00",
          "status": "na",
          "publication": "2020-01-06T09:51:00",
          "weight": "180 to 210 pounds",
          "caution": null,
          "possible_states": null,
          "scars_and_marks": "The unidentified individual had a tattoo of a cross on his neck below his right ear.",
          "race_raw": "Black",
          "files": [
              {
                  "url": "https://www.fbi.gov/wanted/vicap/homicides-and-sexual-assaults/unidentified-individual---albuquerque-new-mexico/vicap-albuquerque-nm-1-6-20.pdf",
                  "name": "English"
              }
          ],
          "field_offices": null,
          "nationality": null,
          "weight_min": 180,
          "age_range": "30 to 45 years old",
          "uid": "775f6a1741e94098b725720e59c8fa22",
          "eyes_raw": null,
          "height_max": 74,
          "height_min": 70,
          "aliases": null,
          "reward_text": null,
          "description": "Albuquerque, New Mexico\r\nMay 1, 2019",
          "title": "UNIDENTIFIED INDIVIDUAL - ALBUQUERQUE, NEW MEXICO",
          "possible_countries": null,
          "hair_raw": "Black",
          "remarks": "<p>The unidentified individual spoke with an accent, possibly Haitian or Dominican. He wore a black hat, a black shirt, and jean shorts. He drove a Peterbilt flatbed tractor trailer truck.</p>",
          "weight_max": 210,
          "age_max": 45,
          "url": "https://www.fbi.gov/wanted/vicap/homicides-and-sexual-assaults/unidentified-individual---albuquerque-new-mexico",
          "ncic": null,
          "eyes": null,
          "sex": "Male",
          "coordinates": [],
          "path": "/wanted/vicap/homicides-and-sexual-assaults/unidentified-individual---albuquerque-new-mexico",
          "place_of_birth": null,
          "reward_min": 0,
          "locations": null,
          "languages": null,
          "subjects": [
              "ViCAP Homicides and Sexual Assaults"
          ],
          "additional_information": null,
          "reward_max": 0,
          "@id": "https://api.fbi.gov/@wanted-person/775f6a1741e94098b725720e59c8fa22"
      },
      {
          "age_range": "22 years old (time of incident)",
          "subjects": [
              "ViCAP Missing Persons"
          ],
          "languages": null,
          "path": "/wanted/vicap/missing-persons/debra-kay-king",
          "weight_min": 110,
          "details": "<p>On July 26, 1982, 22-year-old Debra Kay King was last seen by her sister-in-law. On August 12, 1982, she was reported missing and has not been heard from since. She leaves behind a son and foul play is suspected.</p>",
          "status": "na",
          "possible_states": null,
          "eyes": "brown",
          "hair": "blond",
          "legat_names": null,
          "eyes_raw": "Brown",
          "field_offices": null,
          "weight": "110 pounds (approximately)",
          "age_min": 22,
          "build": null,
          "person_classification": "Main",
          "remarks": null,
          "possible_countries": null,
          "url": "https://www.fbi.gov/wanted/vicap/missing-persons/debra-kay-king",
          "nationality": null,
          "uid": "70c72500b5c642458cbf733fc240e383",
          "warning_message": null,
          "scars_and_marks": "King has a scar on her abdomen and an unknown tattoo on her left hand.",
          "race": "white",
          "hair_raw": "Blonde (possibly dyed)",
          "modified": "2020-01-06T14:05:28+00:00",
          "title": "DEBRA KAY KING - TACOMA, WASHINGTON",
          "images": [
              {
                  "large": "https://www.fbi.gov/wanted/vicap/missing-persons/debra-kay-king/@@images/image/large",
                  "caption": null,
                  "original": "https://www.fbi.gov/wanted/vicap/missing-persons/debra-kay-king/@@images/image",
                  "thumb": "https://www.fbi.gov/wanted/vicap/missing-persons/debra-kay-king/@@images/image/thumb"
              }
          ],
          "complexion": null,
          "reward_text": null,
          "locations": null,
          "suspects": null,
          "additional_information": null,
          "caution": null,
          "reward_max": 0,
          "ncic": null,
          "aliases": null,
          "height_max": 64,
          "dates_of_birth_used": null,
          "height_min": 64,
          "files": [
              {
                  "url": "https://www.fbi.gov/wanted/vicap/missing-persons/debra-kay-king/vicap-king-1-6-20.pdf",
                  "name": "English"
              }
          ],
          "occupations": null,
          "publication": "2017-03-14T13:08:00",
          "description": "Tacoma, Washington\r\nJuly 26, 1982",
          "race_raw": "White",
          "age_max": 22,
          "coordinates": [],
          "place_of_birth": null,
          "reward_min": 0,
          "weight_max": 110,
          "sex": "Female",
          "@id": "https://api.fbi.gov/@wanted-person/70c72500b5c642458cbf733fc240e383"
      },
      {
          "age_range": "27 years old (time of incident)",
          "subjects": [
              "ViCAP Missing Persons"
          ],
          "languages": null,
          "path": "/wanted/vicap/missing-persons/helen-irene-tucker",
          "weight_min": 115,
          "details": "<p>In April of 2000, Helen Irene Tucker, aka Helen Cook, was reported missing. She was last seen on January 20, 1994, at the age of 27. Her last known location was in Tacoma, Washington, along Puyallup Avenue.</p>",
          "status": "na",
          "possible_states": null,
          "eyes": "blue",
          "hair": "brown",
          "legat_names": null,
          "eyes_raw": "Blue",
          "field_offices": null,
          "weight": "115 pounds (approximately)",
          "age_min": 27,
          "build": null,
          "person_classification": "Main",
          "remarks": "<p>Tucker is missing two teeth, one upper and one lower. She has fillings in twelve teeth.</p>",
          "possible_countries": null,
          "url": "https://www.fbi.gov/wanted/vicap/missing-persons/helen-irene-tucker",
          "nationality": null,
          "uid": "e86a6f40f3ba4faca4c301a97e06db4f",
          "warning_message": null,
          "scars_and_marks": "Tucker has a tattoo on a gnome on her left arm, and a rose on her right arm.",
          "race": "white",
          "hair_raw": "Brown",
          "modified": "2020-01-06T13:58:22+00:00",
          "title": "HELEN IRENE TUCKER - TACOMA, WASHINGTON",
          "images": [
              {
                  "large": "https://www.fbi.gov/wanted/vicap/missing-persons/helen-irene-tucker/@@images/image/large",
                  "caption": null,
                  "original": "https://www.fbi.gov/wanted/vicap/missing-persons/helen-irene-tucker/@@images/image",
                  "thumb": "https://www.fbi.gov/wanted/vicap/missing-persons/helen-irene-tucker/@@images/image/thumb"
              }
          ],
          "complexion": null,
          "reward_text": null,
          "locations": null,
          "suspects": null,
          "additional_information": null,
          "caution": null,
          "reward_max": 0,
          "ncic": null,
          "aliases": [
              "Helen Cook"
          ],
          "height_max": 63,
          "dates_of_birth_used": null,
          "height_min": 63,
          "files": [
              {
                  "url": "https://www.fbi.gov/wanted/vicap/missing-persons/helen-irene-tucker/vicap-tucker-1-6-20.pdf",
                  "name": "English"
              }
          ],
          "occupations": null,
          "publication": "2017-03-14T13:18:00",
          "description": "January 20, 1994\r\nTacoma, Washington",
          "race_raw": "White",
          "age_max": 27,
          "coordinates": [],
          "place_of_birth": null,
          "reward_min": 0,
          "weight_max": 115,
          "sex": "Female",
          "@id": "https://api.fbi.gov/@wanted-person/e86a6f40f3ba4faca4c301a97e06db4f"
      },
      {
          "age_range": null,
          "subjects": [
              "Law Enforcement Assistance"
          ],
          "languages": [
              "English",
              "Spanish"
          ],
          "path": "/wanted/law-enforcement-assistance/juan-carlos-ramirez",
          "weight_min": 185,
          "details": null,
          "status": "na",
          "possible_states": null,
          "eyes": "brown",
          "hair": "black",
          "legat_names": null,
          "eyes_raw": "Brown",
          "field_offices": [
              "phoenix"
          ],
          "weight": "185 to 210 pounds",
          "age_min": null,
          "build": null,
          "person_classification": "Main",
          "remarks": null,
          "possible_countries": null,
          "url": "https://www.fbi.gov/wanted/law-enforcement-assistance/juan-carlos-ramirez",
          "nationality": null,
          "uid": "13704e19c9c64c5285434b101bbe0e80",
          "warning_message": null,
          "scars_and_marks": null,
          "race": "hispanic",
          "hair_raw": "Black",
          "modified": "2019-12-16T20:05:37+00:00",
          "title": "JUAN CARLOS RAMIREZ",
          "images": [
              {
                  "large": "https://www.fbi.gov/wanted/law-enforcement-assistance/juan-carlos-ramirez/@@images/image/large",
                  "caption": "Photograph taken in 2017",
                  "original": "https://www.fbi.gov/wanted/law-enforcement-assistance/juan-carlos-ramirez/@@images/image",
                  "thumb": "https://www.fbi.gov/wanted/law-enforcement-assistance/juan-carlos-ramirez/@@images/image/thumb"
              },
              {
                  "large": "https://www.fbi.gov/wanted/law-enforcement-assistance/juan-carlos-ramirez/ramirez2.png/@@images/image/large",
                  "caption": "",
                  "original": "https://www.fbi.gov/wanted/law-enforcement-assistance/juan-carlos-ramirez/ramirez2.png",
                  "thumb": "https://www.fbi.gov/wanted/law-enforcement-assistance/juan-carlos-ramirez/ramirez2.png/@@images/image/thumb"
              }
          ],
          "complexion": null,
          "reward_text": null,
          "locations": null,
          "suspects": null,
          "additional_information": null,
          "caution": "<p>The FBI's Phoenix Field Office and the Tempe Police Department in Arizona are searching for Juan Carlos Ramirez. Ramirez is wanted for his alleged involvement in the theft from a Brink's armored vehicle on October 27, 2019, at approximately 12:09 p.m., in Tempe, Arizona. The vehicle was located a short distance away, abandoned, with money missing.</p>\r\n<p>On November 7, 2019, Ramirez was charged with theft and conspiracy to commit theft by the Superior Court of Maricopa County, and an Arizona state warrant was issued for his arrest.</p>",
          "reward_max": 0,
          "ncic": null,
          "aliases": null,
          "height_max": 70,
          "dates_of_birth_used": [
              "June 19, 1999"
          ],
          "height_min": 69,
          "files": [
              {
                  "url": "https://www.fbi.gov/wanted/law-enforcement-assistance/juan-carlos-ramirez/download.pdf",
                  "name": "English"
              },
              {
                  "url": "https://www.fbi.gov/wanted/law-enforcement-assistance/juan-carlos-ramirez/ramirez-spanish-11-25-19.pdf/@@download/file/Ramirez Spanish 11-25-19.pdf",
                  "name": "EN ESPAÑOL"
              }
          ],
          "occupations": null,
          "publication": "2019-11-13T10:04:00",
          "description": "Theft, Conspiracy to Commit Theft",
          "race_raw": "White (Hispanic)",
          "age_max": null,
          "coordinates": [],
          "place_of_birth": null,
          "reward_min": 0,
          "weight_max": 210,
          "sex": "Male",
          "@id": "https://api.fbi.gov/@wanted-person/13704e19c9c64c5285434b101bbe0e80"
      },
      {
          "eyes": "brown",
          "sex": "Female",
          "age_max": null,
          "url": "https://www.fbi.gov/wanted/kidnap/vanessa-morales",
          "ncic": null,
          "path": "/wanted/kidnap/vanessa-morales",
          "locations": null,
          "weight_min": 17,
          "place_of_birth": null,
          "reward_min": 0,
          "subjects": [
              "Kidnappings and Missing Persons"
          ],
          "additional_information": null,
          "reward_max": 0,
          "languages": null,
          "uid": "7a35a6b20b1841b797e36843a49214dc",
          "eyes_raw": "Brown",
          "height_max": 26,
          "nationality": null,
          "age_range": null,
          "height_min": 26,
          "aliases": null,
          "reward_text": null,
          "possible_countries": null,
          "description": "December 2, 2019\r\nAnsonia, Connecticut",
          "caution": null,
          "weight_max": 17,
          "legat_names": null,
          "race": "hispanic",
          "modified": "2019-12-06T18:18:36+00:00",
          "publication": "2019-12-05T09:47:00",
          "weight": "17 pounds",
          "status": "na",
          "possible_states": null,
          "scars_and_marks": null,
          "images": [
              {
                  "thumb": "https://www.fbi.gov/wanted/kidnap/vanessa-morales/@@images/image/thumb",
                  "original": "https://www.fbi.gov/wanted/kidnap/vanessa-morales/@@images/image",
                  "caption": null,
                  "large": "https://www.fbi.gov/wanted/kidnap/vanessa-morales/@@images/image/large"
              }
          ],
          "remarks": null,
          "files": [
              {
                  "name": "English",
                  "url": "https://www.fbi.gov/wanted/kidnap/vanessa-morales/download.pdf"
              }
          ],
          "field_offices": [
              "newhaven"
          ],
          "coordinates": [],
          "race_raw": "White (Hispanic)",
          "hair_raw": "Brown",
          "complexion": null,
          "build": null,
          "person_classification": "Victim",
          "dates_of_birth_used": [
              "September 7, 2018"
          ],
          "details": "<p>Law enforcement authorities are searching for 1-year-old Vanessa Morales from Ansonia, Connecticut, after finding her mother deceased in their home on December 2, 2019.  Vanessa was last seen by family members on Friday, November 29, 2019.</p>\r\n<p> </p>",
          "warning_message": null,
          "suspects": null,
          "age_min": null,
          "hair": "brown",
          "title": "VANESSA MORALES",
          "occupations": null,
          "@id": "https://api.fbi.gov/@wanted-person/7a35a6b20b1841b797e36843a49214dc"
      },
      {
          "eyes": "brown",
          "sex": "Male",
          "age_max": null,
          "url": "https://www.fbi.gov/wanted/cyber/igor-olegovich-turashev",
          "ncic": null,
          "path": "/wanted/cyber/igor-olegovich-turashev",
          "locations": null,
          "weight_min": null,
          "place_of_birth": "Yoshkar-Ola, Russia",
          "reward_min": 0,
          "subjects": [
              "Cyber's Most Wanted"
          ],
          "additional_information": null,
          "reward_max": 0,
          "languages": null,
          "uid": "0e1142419a964eb182fecfbd064d2de4",
          "eyes_raw": "Brown",
          "height_max": 70,
          "nationality": "Russian",
          "age_range": null,
          "height_min": 70,
          "aliases": [
              "Enki",
              "Parasurama",
              "Nintutu",
              "Vzalupkin",
              "Tigrr",
              "Tigrruz   "
          ],
          "reward_text": null,
          "possible_countries": null,
          "description": "Conspiracy; Conspiracy to Commit Fraud; Wire Fraud; Bank Fraud; Intentional Damage to a Computer",
          "caution": "<p>Igor Olegovich Turashev is wanted for his involvement with computer malware which infected tens of thousands of computers, in both North America and Europe, resulting in financial losses in the tens of millions of dollars. Turashev allegedly handled a variety of responsibilities for the Bugat/Cridex/Dridex malware conspiracy including system administration, management of internal control panels, and oversight of the botnet operations. He allegedly conspired to disseminate the malware through phishing emails, to use the malware to capture online banking credentials, and to use these captured credentials to steal money from the victims’ bank accounts.  He, subsequently, used the malware to install ransomware on victims’ computers.</p>\r\n<p> </p>\r\n<p>Turashev was indicted in the Western District of Pennsylvania, on November 13, 2019, and was charged with Conspiracy, Conspiracy to Commit Fraud, Wire Fraud, Bank Fraud, and Intentional Damage to a Computer.</p>\r\n<p> </p>",
          "weight_max": null,
          "legat_names": null,
          "race": "white",
          "modified": "2019-12-05T14:56:03+00:00",
          "publication": "2019-04-29T10:30:00",
          "weight": null,
          "status": "na",
          "possible_states": null,
          "scars_and_marks": null,
          "images": [
              {
                  "thumb": "https://www.fbi.gov/wanted/cyber/igor-olegovich-turashev/@@images/image/thumb",
                  "original": "https://www.fbi.gov/wanted/cyber/igor-olegovich-turashev/@@images/image",
                  "caption": null,
                  "large": "https://www.fbi.gov/wanted/cyber/igor-olegovich-turashev/@@images/image/large"
              }
          ],
          "remarks": null,
          "files": [
              {
                  "name": "English",
                  "url": "https://www.fbi.gov/wanted/cyber/igor-olegovich-turashev/turashevweb.pdf"
              },
              {
                  "name": "НА РУССКОМ",
                  "url": "https://www.fbi.gov/wanted/cyber/igor-olegovich-turashev/turashevrussian.pdf/@@download/file/TurashevRussian.pdf"
              },
              {
                  "name": "на українській мові",
                  "url": "https://www.fbi.gov/wanted/cyber/igor-olegovich-turashev/turashevukrainian.pdf/@@download/file/TurashevUkrainian.pdf"
              }
          ],
          "field_offices": [
              "pittsburgh"
          ],
          "coordinates": [],
          "race_raw": "White",
          "hair_raw": "Brown",
          "complexion": null,
          "build": null,
          "person_classification": "Main",
          "dates_of_birth_used": [
              "June 15, 1981"
          ],
          "details": null,
          "warning_message": null,
          "suspects": null,
          "age_min": null,
          "hair": "brown",
          "title": "IGOR OLEGOVICH TURASHEV",
          "occupations": null,
          "@id": "https://api.fbi.gov/@wanted-person/0e1142419a964eb182fecfbd064d2de4"
      },
      {
          "eyes": "brown",
          "sex": "Male",
          "age_max": null,
          "url": "https://www.fbi.gov/wanted/law-enforcement-assistance/diego-alfonso-de-leon-mejia",
          "ncic": null,
          "path": "/wanted/law-enforcement-assistance/diego-alfonso-de-leon-mejia",
          "locations": null,
          "weight_min": 150,
          "place_of_birth": null,
          "reward_min": 0,
          "subjects": [
              "Law Enforcement Assistance"
          ],
          "additional_information": null,
          "reward_max": 0,
          "languages": null,
          "uid": "85fd4428f35d4499ab0bd03894d228fe",
          "eyes_raw": "Brown",
          "height_max": 66,
          "nationality": null,
          "age_range": null,
          "height_min": 66,
          "aliases": [
              "Diego Deleon",
              "Diego A. De Leon"
          ],
          "reward_text": null,
          "possible_countries": null,
          "description": "Murder; Possession of a Weapon for Unlawful Purpose",
          "caution": "<p>The FBI's Newark Field Office is assisting the Paterson Police Department and the Passaic County Prosecutor's Office in New Jersey with their search for Diego Alfonso De Leon Mejia.  He is wanted for his alleged involvement in the murder of another man at a gas station in Paterson, New Jersey, on May 16, 2019.  The victim was shot and killed.</p>\r\n<p> </p>\r\n<p>On May 31, 2019, Diego Alfonso De Leon Mejia was charged with murder and possession of a weapon for unlawful purpose by the Paterson Municipal Court, State of New Jersey, and a state warrant was issued for his arrest.</p>\r\n<p> </p>",
          "weight_max": 160,
          "legat_names": null,
          "race": "black",
          "modified": "2019-12-04T21:19:44+00:00",
          "publication": "2019-06-19T08:48:00",
          "weight": "150 to 160 pounds",
          "status": "na",
          "possible_states": null,
          "scars_and_marks": null,
          "images": [
              {
                  "thumb": "https://www.fbi.gov/wanted/law-enforcement-assistance/diego-alfonso-de-leon-mejia/@@images/image/thumb",
                  "original": "https://www.fbi.gov/wanted/law-enforcement-assistance/diego-alfonso-de-leon-mejia/@@images/image",
                  "caption": null,
                  "large": "https://www.fbi.gov/wanted/law-enforcement-assistance/diego-alfonso-de-leon-mejia/@@images/image/large"
              },
              {
                  "thumb": "https://www.fbi.gov/wanted/law-enforcement-assistance/diego-alfonso-de-leon-mejia/deleon2.jpg/@@images/image/thumb",
                  "original": "https://www.fbi.gov/wanted/law-enforcement-assistance/diego-alfonso-de-leon-mejia/deleon2.jpg",
                  "caption": "",
                  "large": "https://www.fbi.gov/wanted/law-enforcement-assistance/diego-alfonso-de-leon-mejia/deleon2.jpg/@@images/image/large"
              }
          ],
          "remarks": null,
          "files": [
              {
                  "name": "English",
                  "url": "https://www.fbi.gov/wanted/law-enforcement-assistance/diego-alfonso-de-leon-mejia/download.pdf"
              }
          ],
          "field_offices": [
              "newark"
          ],
          "coordinates": [],
          "race_raw": "Black",
          "hair_raw": "Brown",
          "complexion": null,
          "build": null,
          "person_classification": "Main",
          "dates_of_birth_used": [
              "May 29, 1999"
          ],
          "details": null,
          "warning_message": "SHOULD BE CONSIDERED ARMED AND DANGEROUS",
          "suspects": null,
          "age_min": null,
          "hair": "brown",
          "title": "DIEGO ALFONSO DE LEON MEJIA",
          "occupations": null,
          "@id": "https://api.fbi.gov/@wanted-person/85fd4428f35d4499ab0bd03894d228fe"
      },
      {
          "eyes": "blue",
          "sex": "Male",
          "age_max": null,
          "url": "https://www.fbi.gov/wanted/wcc/craig-john-oliver",
          "ncic": "W178502753",
          "path": "/wanted/wcc/craig-john-oliver",
          "locations": null,
          "weight_min": 190,
          "place_of_birth": "Washington, D.C.",
          "reward_min": 0,
          "subjects": [
              "White-Collar Crime"
          ],
          "additional_information": null,
          "reward_max": 0,
          "languages": null,
          "uid": "c09e3768c8fb796f946f1f4fcd909ee7",
          "eyes_raw": "Blue",
          "height_max": 74,
          "nationality": "American",
          "age_range": null,
          "height_min": 74,
          "aliases": [
              "John Oliver",
              "Craig J. Oliver",
              "Leigh Owsley",
              "Bernard Owsley",
              "Mel Merlowe",
              "Danny Sullivan",
              "Daniel Sullivan"
          ],
          "reward_text": null,
          "possible_countries": null,
          "description": "Violation of Release Conditions (Fraud By Wire)",
          "caution": "<p>On October 3, 2005, Craig John Oliver, a convicted felon, plead guilty in the United States District Court, Eastern District of Virginia, to defrauding 68 Virginia and Maryland homeowners of more than $2.5 million.  The victims were clients of Oliver's home renovation businesses. From 2002 until 2005, Oliver used fraudulent business licenses and induced clients to make payments for work which was never completed.   Oliver was released from jail on bond, but violated his release conditions and a warrant was issued for his arrest on December 6, 2005. Oliver failed to appear in court on January 20, 2006, as scheduled, and was sentenced in absentia to 20 years in Federal prison.  It is believed that Oliver fled the Fairfax, Virginia, area in November of 2005.</p>\r\n<p> </p>\r\n<p>Oliver is also wanted for probation violation in 1995 which followed a securities fraud conviction in Arlington County, Virginia.</p>\r\n<p> </p>\r\n<p>On September 19, 2016, the FBI received information suggesting that Oliver and his wife, Jennifer Oliver, were living and conducting business in the Los Angeles, California, area, to include the cities of Culver City and Gardena, California.  Investigators believe that Oliver was alerted to some recent publicity and fled once again.  Upon arrival at a possible business location, law enforcement officials were advised that the couple had been there earlier the same day to pick up a check and mentioned they were leaving town, possibly to Georgia. The FBI believes that the couple may also have ties to Nevada.</p>\r\n<p> </p>",
          "weight_max": 190,
          "legat_names": null,
          "race": "white",
          "modified": "2019-12-04T21:02:26+00:00",
          "publication": "2010-08-17T03:35:00",
          "weight": "190 pounds",
          "status": "na",
          "possible_states": null,
          "scars_and_marks": "Oliver has a scar on his right ankle.",
          "images": [
              {
                  "thumb": "https://www.fbi.gov/wanted/wcc/craig-john-oliver/@@images/image/thumb",
                  "original": "https://www.fbi.gov/wanted/wcc/craig-john-oliver/@@images/image",
                  "caption": "Photograph taken in 2014",
                  "large": "https://www.fbi.gov/wanted/wcc/craig-john-oliver/@@images/image/large"
              },
              {
                  "thumb": "https://www.fbi.gov/wanted/wcc/craig-john-oliver/oliver_cj1.jpg/@@images/image/thumb",
                  "original": "https://www.fbi.gov/wanted/wcc/craig-john-oliver/oliver_cj1.jpg",
                  "caption": "Photograph taken in 2005",
                  "large": "https://www.fbi.gov/wanted/wcc/craig-john-oliver/oliver_cj1.jpg/@@images/image/large"
              },
              {
                  "thumb": "https://www.fbi.gov/wanted/wcc/craig-john-oliver/oliver_c_j6.jpg/@@images/image/thumb",
                  "original": "https://www.fbi.gov/wanted/wcc/craig-john-oliver/oliver_c_j6.jpg",
                  "caption": "Craig and Jennifer Oliver",
                  "large": "https://www.fbi.gov/wanted/wcc/craig-john-oliver/oliver_c_j6.jpg/@@images/image/large"
              },
              {
                  "thumb": "https://www.fbi.gov/wanted/wcc/craig-john-oliver/oliver-wife-2019.png/@@images/image/thumb",
                  "original": "https://www.fbi.gov/wanted/wcc/craig-john-oliver/oliver-wife-2019.png",
                  "caption": "Jennifer Oliver - Photograph taken in 2016",
                  "large": "https://www.fbi.gov/wanted/wcc/craig-john-oliver/oliver-wife-2019.png/@@images/image/large"
              },
              {
                  "thumb": "https://www.fbi.gov/wanted/wcc/craig-john-oliver/oliver_jl4.jpg/@@images/image/thumb",
                  "original": "https://www.fbi.gov/wanted/wcc/craig-john-oliver/oliver_jl4.jpg",
                  "caption": "Jennifer Oliver - Photograph taken in 2003",
                  "large": "https://www.fbi.gov/wanted/wcc/craig-john-oliver/oliver_jl4.jpg/@@images/image/large"
              },
              {
                  "thumb": "https://www.fbi.gov/wanted/wcc/craig-john-oliver/oliver2014b.jpg/@@images/image/thumb",
                  "original": "https://www.fbi.gov/wanted/wcc/craig-john-oliver/oliver2014b.jpg",
                  "caption": "Photograph taken in 2014",
                  "large": "https://www.fbi.gov/wanted/wcc/craig-john-oliver/oliver2014b.jpg/@@images/image/large"
              },
              {
                  "thumb": "https://www.fbi.gov/wanted/wcc/craig-john-oliver/oliver_cj3.jpg/@@images/image/thumb",
                  "original": "https://www.fbi.gov/wanted/wcc/craig-john-oliver/oliver_cj3.jpg",
                  "caption": "Photograph taken in 2003",
                  "large": "https://www.fbi.gov/wanted/wcc/craig-john-oliver/oliver_cj3.jpg/@@images/image/large"
              },
              {
                  "thumb": "https://www.fbi.gov/wanted/wcc/craig-john-oliver/oliver_cj2.jpg/@@images/image/thumb",
                  "original": "https://www.fbi.gov/wanted/wcc/craig-john-oliver/oliver_cj2.jpg",
                  "caption": "Photograph taken in 2005",
                  "large": "https://www.fbi.gov/wanted/wcc/craig-john-oliver/oliver_cj2.jpg/@@images/image/large"
              },
              {
                  "thumb": "https://www.fbi.gov/wanted/wcc/craig-john-oliver/oliver.jpg/@@images/image/thumb",
                  "original": "https://www.fbi.gov/wanted/wcc/craig-john-oliver/oliver.jpg",
                  "caption": "Photograph taken in 2007",
                  "large": "https://www.fbi.gov/wanted/wcc/craig-john-oliver/oliver.jpg/@@images/image/large"
              },
              {
                  "thumb": "https://www.fbi.gov/wanted/wcc/craig-john-oliver/oliver_c_j5.jpg/@@images/image/thumb",
                  "original": "https://www.fbi.gov/wanted/wcc/craig-john-oliver/oliver_c_j5.jpg",
                  "caption": "Craig and Jennifer Oliver",
                  "large": "https://www.fbi.gov/wanted/wcc/craig-john-oliver/oliver_c_j5.jpg/@@images/image/large"
              },
              {
                  "thumb": "https://www.fbi.gov/wanted/wcc/craig-john-oliver/oliver_jl5.jpg/@@images/image/thumb",
                  "original": "https://www.fbi.gov/wanted/wcc/craig-john-oliver/oliver_jl5.jpg",
                  "caption": "Jennifer Oliver - Photograph taken in 2007",
                  "large": "https://www.fbi.gov/wanted/wcc/craig-john-oliver/oliver_jl5.jpg/@@images/image/large"
              }
          ],
          "remarks": "<p>Oliver may wear a mustache. </p>\r\n<p>Oliver's wife, Jennifer Oliver, who is not a fugitive from the law, is believed to be traveling with him and may go by the alias Tara Jean.  There is a large height disparity between the couple as he is 6'2\" and she is only 4'11\".  They may have traveled to California, Nevada, or Georgia, and are likely living in a warm climate as they are not known to like the cold weather.  They are known to like cats.</p>",
          "files": [
              {
                  "name": "English",
                  "url": "https://www.fbi.gov/wanted/wcc/craig-john-oliver/download.pdf"
              }
          ],
          "field_offices": [
              "washingtondc"
          ],
          "coordinates": [],
          "race_raw": "White",
          "hair_raw": "Brown/Gray (Balding)",
          "complexion": null,
          "build": null,
          "person_classification": "Main",
          "dates_of_birth_used": [
              "February 14, 1953"
          ],
          "details": null,
          "warning_message": null,
          "suspects": null,
          "age_min": null,
          "hair": "brown",
          "title": "CRAIG JOHN OLIVER",
          "occupations": [
              "Home Improvement Sales, Construction, Interior Decorating, Remodeling, Window and Door Consultant"
          ],
          "@id": "https://api.fbi.gov/@wanted-person/c09e3768c8fb796f946f1f4fcd909ee7"
      },
      {
          "eyes": "brown",
          "sex": "Male",
          "age_max": null,
          "url": "https://www.fbi.gov/wanted/murders/cesar-soltero-herrera",
          "ncic": "W252087737",
          "path": "/wanted/murders/cesar-soltero-herrera",
          "locations": null,
          "weight_min": 160,
          "place_of_birth": "Los Angeles, California",
          "reward_min": 0,
          "subjects": [
              "Violent Crimes - Murders"
          ],
          "additional_information": null,
          "reward_max": 0,
          "languages": null,
          "uid": "eeb83b8395a04966bd8ca9aa6023b7f8",
          "eyes_raw": "Brown",
          "height_max": 70,
          "nationality": "American",
          "age_range": null,
          "height_min": 70,
          "aliases": [
              "\"Jumps\"",
              "Cesar Cortes",
              "Cesar Herrera",
              "Cesar Soltero",
              "Cesar Soltero-Herrera",
              "Cesar Hidalgo"
          ],
          "reward_text": "The FBI is offering a reward of up to $5,000 for information leading to the arrest of Cesar Soltero Herrera.",
          "possible_countries": null,
          "description": "Unlawful Flight to Avoid Prosecution - Murder, Attempted Murder",
          "caution": "<p>Cesar Soltero Herrera is wanted for his alleged involvement in a murder and attempted murder in 2007.</p>\r\n<p> </p>\r\n<p>On February 19, 2007, in North Hollywood, California, Herrera became involved in a physical altercation with a male victim when the victim struck Herrera and caused him to bleed from the nose. Herrera then allegedly left the scene but returned a short time later with a semi-automatic handgun and fired multiple shots at the male victim and others, killing the victim.</p>\r\n<p> </p>\r\n<p>Herrera was charged with one count of murder and two counts of attempted murder by the Superior Court of California, County of Los Angeles, and a state warrant was issued for his arrest on February 21, 2007. A federal arrest warrant was issued by the United States District Court, Central District of California, Los Angeles, California, on April 26, 2007, after Herrera was charged federally with unlawful flight to avoid prosecution.</p>",
          "weight_max": 160,
          "legat_names": null,
          "race": "hispanic",
          "modified": "2019-12-04T15:51:02+00:00",
          "publication": "2019-02-05T10:57:00",
          "weight": "160 pounds",
          "status": "na",
          "possible_states": null,
          "scars_and_marks": "Herrera has a tattoo of a cross on his left arm, a word on his left breast, and a tattoo on his right arm.",
          "images": [
              {
                  "thumb": "https://www.fbi.gov/wanted/murders/cesar-soltero-herrera/@@images/image/thumb",
                  "original": "https://www.fbi.gov/wanted/murders/cesar-soltero-herrera/@@images/image",
                  "caption": "Photograph taken in 2006",
                  "large": "https://www.fbi.gov/wanted/murders/cesar-soltero-herrera/@@images/image/large"
              }
          ],
          "remarks": "<p>Herrera may be residing in, and has ties to, Mexico. He has previously resided in North Hollywood, California.</p>",
          "files": [
              {
                  "name": "English",
                  "url": "https://www.fbi.gov/wanted/murders/cesar-soltero-herrera/download.pdf"
              },
              {
                  "name": "EN ESPAÑOL",
                  "url": "https://www.fbi.gov/wanted/murders/cesar-soltero-herrera/herrera-spanish-3-27-19.pdf/@@download/file/Herrera Spanish 3-27-19.pdf"
              }
          ],
          "field_offices": [
              "losangeles"
          ],
          "coordinates": [],
          "race_raw": "White (Hispanic)",
          "hair_raw": "Black",
          "complexion": null,
          "build": null,
          "person_classification": "Main",
          "dates_of_birth_used": [
              "April 18, 1988"
          ],
          "details": null,
          "warning_message": "SHOULD BE CONSIDERED ARMED AND DANGEROUS",
          "suspects": null,
          "age_min": null,
          "hair": "black",
          "title": "CESAR SOLTERO HERRERA",
          "occupations": null,
          "@id": "https://api.fbi.gov/@wanted-person/eeb83b8395a04966bd8ca9aa6023b7f8"
      },
      {
          "eyes": "brown",
          "sex": "Male",
          "age_max": null,
          "url": "https://www.fbi.gov/wanted/cyber/maksim-viktorovich-yakubets",
          "ncic": null,
          "path": "/wanted/cyber/maksim-viktorovich-yakubets",
          "locations": null,
          "weight_min": 170,
          "place_of_birth": "Ukraine",
          "reward_min": 0,
          "subjects": [
              "Cyber's Most Wanted"
          ],
          "additional_information": null,
          "reward_max": 0,
          "languages": null,
          "uid": "f0ac1b1e81e74cfa9f4d26a0a0a308e6",
          "eyes_raw": "Brown",
          "height_max": 70,
          "nationality": "Russian",
          "age_range": null,
          "height_min": 70,
          "aliases": [
              "Maksim Yakubets",
              "\"AQUA\""
          ],
          "reward_text": "The United States Department of State’s Transnational Organized Crime Rewards Program is offering a reward of up to $5 million for information leading to the arrest and/or conviction of Maksim Viktorovich Yakubets.",
          "possible_countries": null,
          "description": "Conspiracy; Conspiracy to Commit Fraud; Wire Fraud; Bank Fraud; Intentional Damage to a Computer",
          "caution": "<p>Maksim Viktorovich Yakubets is wanted for his involvement with computer malware that infected tens of thousands of computers in both North America and Europe, resulting in actual financial losses in the tens of millions of dollars.</p>\r\n<p> </p>\r\n<p>Specifically, Yakubets was involved in the installation of malicious software known as \"Zeus\", which was disseminated through phishing emails and used to capture victims’ online banking credentials.  These credentials were then used to steal money from the victims' bank accounts.  On August 22, 2012, an individual was charged in a superseding indictment under the moniker “aqua” in the District of Nebraska with conspiracy to participate in racketeering activity, conspiracy to commit computer fraud and identity theft, aggravated identity theft, and multiple counts of bank fraud.  On November 14, 2019, a criminal complaint was issued in the District of Nebraska that ties the previously indicted moniker of “aqua” to Yakubets and charges him with conspiracy to commit bank fraud.</p>\r\n<p> </p>\r\n<p>Yakubets is also allegedly the leader of the Bugat/Cridex/Dridex malware conspiracy wherein he oversaw and managed the development, maintenance, distribution, and infection of the malware.  Yakubets allegedly conspired to disseminate the malware through phishing emails, to use the malware to capture online banking credentials, and to use these captured credentials to steal money from the victims’ bank accounts.  He, subsequently, used the malware to install ransomware on victims’ computers.  Yakubets was indicted in the Western District of Pennsylvania, on November 13, 2019, and was charged with Conspiracy, Conspiracy to Commit Fraud, Wire Fraud, Bank Fraud, and Intentional Damage to a Computer.</p>\r\n<p> </p>",
          "weight_max": 170,
          "legat_names": null,
          "race": "white",
          "modified": "2019-12-04T14:52:21+00:00",
          "publication": "2019-04-29T09:25:00",
          "weight": "Approximately 170 pounds",
          "status": "na",
          "possible_states": null,
          "scars_and_marks": null,
          "images": [
              {
                  "thumb": "https://www.fbi.gov/wanted/cyber/maksim-viktorovich-yakubets/@@images/image/thumb",
                  "original": "https://www.fbi.gov/wanted/cyber/maksim-viktorovich-yakubets/@@images/image",
                  "caption": null,
                  "large": "https://www.fbi.gov/wanted/cyber/maksim-viktorovich-yakubets/@@images/image/large"
              },
              {
                  "thumb": "https://www.fbi.gov/wanted/cyber/maksim-viktorovich-yakubets/yakubets3a.jpg/@@images/image/thumb",
                  "original": "https://www.fbi.gov/wanted/cyber/maksim-viktorovich-yakubets/yakubets3a.jpg",
                  "caption": "",
                  "large": "https://www.fbi.gov/wanted/cyber/maksim-viktorovich-yakubets/yakubets3a.jpg/@@images/image/large"
              },
              {
                  "thumb": "https://www.fbi.gov/wanted/cyber/maksim-viktorovich-yakubets/yakubets4a.jpg/@@images/image/thumb",
                  "original": "https://www.fbi.gov/wanted/cyber/maksim-viktorovich-yakubets/yakubets4a.jpg",
                  "caption": "",
                  "large": "https://www.fbi.gov/wanted/cyber/maksim-viktorovich-yakubets/yakubets4a.jpg/@@images/image/large"
              },
              {
                  "thumb": "https://www.fbi.gov/wanted/cyber/maksim-viktorovich-yakubets/yakubets2a.jpg/@@images/image/thumb",
                  "original": "https://www.fbi.gov/wanted/cyber/maksim-viktorovich-yakubets/yakubets2a.jpg",
                  "caption": "",
                  "large": "https://www.fbi.gov/wanted/cyber/maksim-viktorovich-yakubets/yakubets2a.jpg/@@images/image/large"
              },
              {
                  "thumb": "https://www.fbi.gov/wanted/cyber/maksim-viktorovich-yakubets/yakubets1a.jpg/@@images/image/thumb",
                  "original": "https://www.fbi.gov/wanted/cyber/maksim-viktorovich-yakubets/yakubets1a.jpg",
                  "caption": "",
                  "large": "https://www.fbi.gov/wanted/cyber/maksim-viktorovich-yakubets/yakubets1a.jpg/@@images/image/large"
              }
          ],
          "remarks": null,
          "files": [
              {
                  "name": "English",
                  "url": "https://www.fbi.gov/wanted/cyber/maksim-viktorovich-yakubets/yakubetsweb.pdf"
              },
              {
                  "name": "НА РУССКОМ",
                  "url": "https://www.fbi.gov/wanted/cyber/maksim-viktorovich-yakubets/yakubetsrussian.pdf/@@download/file/YakubetsRussian.pdf"
              },
              {
                  "name": "на українській мові",
                  "url": "https://www.fbi.gov/wanted/cyber/maksim-viktorovich-yakubets/yakubetsukrainian.pdf/@@download/file/YakubetsUkrainian.pdf"
              }
          ],
          "field_offices": [
              "omaha",
              "pittsburgh"
          ],
          "coordinates": [],
          "race_raw": "White",
          "hair_raw": "Brown",
          "complexion": null,
          "build": null,
          "person_classification": "Main",
          "dates_of_birth_used": [
              "May 20, 1987"
          ],
          "details": null,
          "warning_message": null,
          "suspects": null,
          "age_min": null,
          "hair": "brown",
          "title": "MAKSIM VIKTOROVICH YAKUBETS",
          "occupations": null,
          "@id": "https://api.fbi.gov/@wanted-person/f0ac1b1e81e74cfa9f4d26a0a0a308e6"
      },
      {
          "eyes": "blue",
          "sex": "Male",
          "age_max": null,
          "url": "https://www.fbi.gov/wanted/wanted_terrorists/jehad-serwan-mostafa",
          "ncic": null,
          "path": "/wanted/wanted_terrorists/jehad-serwan-mostafa",
          "locations": null,
          "weight_min": 170,
          "place_of_birth": "Waukesha, Wisconsin",
          "reward_min": 0,
          "subjects": [
              "Most Wanted Terrorists"
          ],
          "additional_information": null,
          "reward_max": 0,
          "languages": [
              "Arabic",
              "Somali",
              "English"
          ],
          "uid": "046cea2c4def4588a880fbaba095813c",
          "eyes_raw": "Blue",
          "height_max": 73,
          "nationality": "American",
          "age_range": null,
          "height_min": 73,
          "aliases": [
              "Emir Anwar",
              "Ahmed Gurey",
              "Anwar al-Amriki",
              "\"Ahmed\" (moniker)",
              "\"Anwar\" (moniker)",
              "Abu Abdullah al-Muhajir"
          ],
          "reward_text": "The Rewards For Justice Program, United States Department of State, is offering a reward of up to $5 million for information leading to Jehad Serwan Mostafa's arrest.",
          "possible_countries": null,
          "description": "Conspiracy to Provide Material Support to Terrorists; Conspiracy to Provide Material Support to a Foreign Terrorist Organization; Providing Material Support to a Foreign Terrorist Organization",
          "caution": "<p>Jehad Serwan Mostafa is believed to be the highest-ranking United States citizen fighting with al-Shabaab, a Somalia-based terrorist organization. It is believed that Mostafa joined al-Shabaab in approximately 2006 and has served in many capacities, including serving as a military instructor at al-Shabaab's training camps, a leader of the foreign fighters, a leader and propagandist in al-Shabaab's media wing, an intermediary between al-Shabaab and other terrorist organizations, and as a leader in the group's use of explosives in terrorist attacks. Mostafa is currently charged in a superseding indictment in the United States District Court, Southern District of California, San Diego, California, with conspiracy to provide material support to terrorists; conspiracy to provide material support to a foreign terrorist organization; and providing material support to a foreign terrorist organization.</p>",
          "weight_max": 170,
          "legat_names": null,
          "race": null,
          "modified": "2019-12-02T20:57:46+00:00",
          "publication": "2010-09-22T15:55:00",
          "weight": "170 pounds",
          "status": "na",
          "possible_states": null,
          "scars_and_marks": "Mostafa is left-handed and has a distinctive scar on his right hand. He wears a full beard and glasses.",
          "images": [
              {
                  "thumb": "https://www.fbi.gov/wanted/wanted_terrorists/jehad-serwan-mostafa/@@images/image/thumb",
                  "original": "https://www.fbi.gov/wanted/wanted_terrorists/jehad-serwan-mostafa/@@images/image",
                  "caption": null,
                  "large": "https://www.fbi.gov/wanted/wanted_terrorists/jehad-serwan-mostafa/@@images/image/large"
              },
              {
                  "thumb": "https://www.fbi.gov/wanted/wanted_terrorists/jehad-serwan-mostafa/mostafa-standing-scarf-3-crop.jpg/@@images/image/thumb",
                  "original": "https://www.fbi.gov/wanted/wanted_terrorists/jehad-serwan-mostafa/mostafa-standing-scarf-3-crop.jpg",
                  "caption": "",
                  "large": "https://www.fbi.gov/wanted/wanted_terrorists/jehad-serwan-mostafa/mostafa-standing-scarf-3-crop.jpg/@@images/image/large"
              },
              {
                  "thumb": "https://www.fbi.gov/wanted/wanted_terrorists/jehad-serwan-mostafa/mostafa-scarf-4-crop.jpg/@@images/image/thumb",
                  "original": "https://www.fbi.gov/wanted/wanted_terrorists/jehad-serwan-mostafa/mostafa-scarf-4-crop.jpg",
                  "caption": "",
                  "large": "https://www.fbi.gov/wanted/wanted_terrorists/jehad-serwan-mostafa/mostafa-scarf-4-crop.jpg/@@images/image/large"
              }
          ],
          "remarks": "<p>Mostafa may have visited, or is likely to visit, the following areas: Somalia, Yemen, Ethiopia, Kenya, and other African countries. Additionally, Mostafa was raised in and graduated from college in San Diego, California.</p>",
          "files": [
              {
                  "name": "English",
                  "url": "https://www.fbi.gov/wanted/wanted_terrorists/jehad-serwan-mostafa/mostafaweb-11-2019.pdf"
              },
              {
                  "name": "AF-SOOMAALI",
                  "url": "https://www.fbi.gov/wanted/wanted_terrorists/jehad-serwan-mostafa/mostafa-somali-12-2-19.pdf/@@download/file/Mostafa Somali 12-2-19.pdf"
              },
              {
                  "name": "KWA KISWAHILI",
                  "url": "https://www.fbi.gov/wanted/wanted_terrorists/jehad-serwan-mostafa/mostafa-swahili-12-2-19.pdf/@@download/file/Mostafa Swahili 12-2-19.pdf"
              }
          ],
          "field_offices": [
              "sandiego"
          ],
          "coordinates": [],
          "race_raw": null,
          "hair_raw": "Brown",
          "complexion": "Light",
          "build": "Tall, thin",
          "person_classification": "Main",
          "dates_of_birth_used": [
              "December 28, 1981"
          ],
          "details": null,
          "warning_message": "SHOULD BE CONSIDERED ARMED AND DANGEROUS",
          "suspects": null,
          "age_min": null,
          "hair": "brown",
          "title": "JEHAD SERWAN MOSTAFA",
          "occupations": null,
          "@id": "https://api.fbi.gov/@wanted-person/046cea2c4def4588a880fbaba095813c"
      },
      {
          "age_range": null,
          "subjects": [
              "Criminal Enterprise Investigations"
          ],
          "languages": null,
          "path": "/wanted/cei/jason-jackson",
          "weight_min": 190,
          "details": null,
          "status": "na",
          "possible_states": null,
          "eyes": "brown",
          "hair": "black",
          "legat_names": null,
          "eyes_raw": "Brown",
          "field_offices": [
              "pittsburgh"
          ],
          "weight": "190 pounds",
          "age_min": null,
          "build": null,
          "person_classification": "Main",
          "remarks": null,
          "possible_countries": null,
          "url": "https://www.fbi.gov/wanted/cei/jason-jackson",
          "nationality": null,
          "uid": "c0dfe01bab46466eb8b8899f33d39e10",
          "warning_message": null,
          "scars_and_marks": null,
          "race": "black",
          "hair_raw": "Black",
          "modified": "2019-12-02T16:39:46+00:00",
          "title": "JASON JACKSON",
          "images": [
              {
                  "large": "https://www.fbi.gov/wanted/cei/jason-jackson/@@images/image/large",
                  "caption": null,
                  "original": "https://www.fbi.gov/wanted/cei/jason-jackson/@@images/image",
                  "thumb": "https://www.fbi.gov/wanted/cei/jason-jackson/@@images/image/thumb"
              }
          ],
          "complexion": null,
          "reward_text": null,
          "locations": null,
          "suspects": null,
          "additional_information": null,
          "caution": "<p>Jason Jackson is wanted for his alleged involvement in drug trafficking in Allegheny County, Pennsylvania, from September of 2017 until November of 2019.  Jackson is an alleged member of a group of drug traffickers identifying themselves as \"Hustlas Don't Sleep\" who sold a variety of controlled substances, including fentanyl, fentanyl analogues, crack cocaine, and heroin, primarily out of the McKeesport, Turtle Creek, Wilkinsburg, and Monroeville areas of Allegheny County.  On November 15, 2019, a federal arrest warrant was issued in the United States District Court for the Western District of Pennsylvania after Jackson was charged with Conspiracy to Distribute One Kilogram or More of Heroin, 280 Grams or More of Crack Cocaine, 100 Grams or More of Acetyl Fentanyl and Valeryl Fentanyl, and 400 Grams or More of Fentanyl.</p>\r\n<p> </p>",
          "reward_max": 0,
          "ncic": "W638363378",
          "aliases": null,
          "height_max": 68,
          "dates_of_birth_used": [
              "July 17, 1990"
          ],
          "height_min": 68,
          "files": [
              {
                  "url": "https://www.fbi.gov/wanted/cei/jason-jackson/download.pdf",
                  "name": "English"
              }
          ],
          "occupations": null,
          "publication": "2019-12-02T09:21:00",
          "description": "Conspiracy to Distribute One Kilogram or More of Heroin, 280 Grams or More of Crack Cocaine, 100 Grams or More of Acetyl Fentanyl and Valeryl Fentanyl, and 400 Grams or More of Fentanyl",
          "race_raw": "Black",
          "age_max": null,
          "coordinates": [],
          "place_of_birth": null,
          "reward_min": 0,
          "weight_max": 190,
          "sex": "Male",
          "@id": "https://api.fbi.gov/@wanted-person/c0dfe01bab46466eb8b8899f33d39e10"
      },
      {
          "eyes": "brown",
          "sex": "Male",
          "age_max": null,
          "url": "https://www.fbi.gov/wanted/counterintelligence/ali-hamad-a-alzabarah",
          "ncic": null,
          "path": "/wanted/counterintelligence/ali-hamad-a-alzabarah",
          "locations": null,
          "weight_min": 205,
          "place_of_birth": "Saudi Arabia",
          "reward_min": 0,
          "subjects": [
              "Counterintelligence"
          ],
          "additional_information": null,
          "reward_max": 0,
          "languages": null,
          "uid": "c00891f136134e76a5eb24c7672de893",
          "eyes_raw": "Brown",
          "height_max": 65,
          "nationality": "Saudi Arabian",
          "age_range": null,
          "height_min": 65,
          "aliases": null,
          "reward_text": null,
          "possible_countries": null,
          "description": "Acting as an Unregistered Agent of a Foreign Government",
          "caution": "<p>Ali Hamad A Alzabarah is wanted for failing to register as an agent of a foreign government as required by United States law.  In 2015, Alzabarah allegedly took part in a scheme to steal proprietary and confidential user data from a U.S. company, Twitter, for the benefit of the Kingdom of Saudi Arabia.  The stolen data included email addresses, telephone numbers and internet protocol addresses of Saudi dissidents and critics of the Saudi government, among others.  A federal arrest warrant was issued for Alzabarah in the United States District Court, Northern District of California, on November 5, 2019, after he was charged with acting as an unregistered agent of a foreign government.</p>\r\n<p> </p>",
          "weight_max": 205,
          "legat_names": null,
          "race": null,
          "modified": "2019-12-02T15:01:15+00:00",
          "publication": "2019-10-28T11:22:00",
          "weight": "205 pounds",
          "status": "na",
          "possible_states": null,
          "scars_and_marks": null,
          "images": [
              {
                  "thumb": "https://www.fbi.gov/wanted/counterintelligence/ali-hamad-a-alzabarah/@@images/image/thumb",
                  "original": "https://www.fbi.gov/wanted/counterintelligence/ali-hamad-a-alzabarah/@@images/image",
                  "caption": "Photograph taken in 2015",
                  "large": "https://www.fbi.gov/wanted/counterintelligence/ali-hamad-a-alzabarah/@@images/image/large"
              },
              {
                  "thumb": "https://www.fbi.gov/wanted/counterintelligence/ali-hamad-a-alzabarah/alzabarah2.jpg/@@images/image/thumb",
                  "original": "https://www.fbi.gov/wanted/counterintelligence/ali-hamad-a-alzabarah/alzabarah2.jpg",
                  "caption": "",
                  "large": "https://www.fbi.gov/wanted/counterintelligence/ali-hamad-a-alzabarah/alzabarah2.jpg/@@images/image/large"
              }
          ],
          "remarks": null,
          "files": [
              {
                  "name": "English",
                  "url": "https://www.fbi.gov/wanted/counterintelligence/ali-hamad-a-alzabarah/download.pdf"
              },
              {
                  "name": "باللغة العربية",
                  "url": "https://www.fbi.gov/wanted/counterintelligence/ali-hamad-a-alzabarah/alzabaraharabic.pdf/@@download/file/alzabaraharabic.pdf"
              }
          ],
          "field_offices": [
              "sanfrancisco"
          ],
          "coordinates": [],
          "race_raw": null,
          "hair_raw": "Black",
          "complexion": null,
          "build": null,
          "person_classification": "Main",
          "dates_of_birth_used": [
              "September 8, 1983"
          ],
          "details": null,
          "warning_message": null,
          "suspects": null,
          "age_min": null,
          "hair": "black",
          "title": "ALI HAMAD A ALZABARAH",
          "occupations": null,
          "@id": "https://api.fbi.gov/@wanted-person/c00891f136134e76a5eb24c7672de893"
      },
      {
          "eyes": null,
          "sex": "Male",
          "age_max": null,
          "url": "https://www.fbi.gov/wanted/counterintelligence/ahmed-saad-m-almutairi",
          "ncic": null,
          "path": "/wanted/counterintelligence/ahmed-saad-m-almutairi",
          "locations": null,
          "weight_min": null,
          "place_of_birth": "Saudi Arabia",
          "reward_min": 0,
          "subjects": [
              "Counterintelligence"
          ],
          "additional_information": null,
          "reward_max": 0,
          "languages": null,
          "uid": "126ac97fa13c4848b3ba66d03dbfd735",
          "eyes_raw": null,
          "height_max": null,
          "nationality": "Saudi Arabian",
          "age_range": null,
          "height_min": null,
          "aliases": [
              "Ahmed Aljbreen"
          ],
          "reward_text": null,
          "possible_countries": null,
          "description": "Acting as an Unregistered Agent of a Foreign Government",
          "caution": "<p>Ahmed Saad M Almutairi, who is more commonly known by the name Ahmed Aljbreen, is wanted for failing to register as an agent of a foreign government as required by United States law.  In 2014 and 2015, Almutairi allegedly took part in a scheme to steal proprietary and confidential user data from a U.S. company, Twitter, for the benefit of the Kingdom of Saudi Arabia.  The stolen data included email addresses, telephone numbers and internet protocol addresses of Saudi dissidents and critics of the Saudi government, among others.  A federal arrest warrant was issued for Almutairi in the United States District Court, Northern District of California, on November 5, 2019, after he was charged with acting as an unregistered agent of a foreign government.</p>\r\n<p> </p>",
          "weight_max": null,
          "legat_names": null,
          "race": null,
          "modified": "2019-12-02T14:59:51+00:00",
          "publication": "2019-10-28T11:59:00",
          "weight": null,
          "status": "na",
          "possible_states": null,
          "scars_and_marks": null,
          "images": [
              {
                  "thumb": "https://www.fbi.gov/wanted/counterintelligence/ahmed-saad-m-almutairi/@@images/image/thumb",
                  "original": "https://www.fbi.gov/wanted/counterintelligence/ahmed-saad-m-almutairi/@@images/image",
                  "caption": "Photograph taken in 2016",
                  "large": "https://www.fbi.gov/wanted/counterintelligence/ahmed-saad-m-almutairi/@@images/image/large"
              }
          ],
          "remarks": null,
          "files": [
              {
                  "name": "English",
                  "url": "https://www.fbi.gov/wanted/counterintelligence/ahmed-saad-m-almutairi/download.pdf"
              },
              {
                  "name": "باللغة العربية",
                  "url": "https://www.fbi.gov/wanted/counterintelligence/ahmed-saad-m-almutairi/almutairiarabic.pdf/@@download/file/almutairiarabic.pdf"
              }
          ],
          "field_offices": [
              "sanfrancisco"
          ],
          "coordinates": [],
          "race_raw": null,
          "hair_raw": null,
          "complexion": null,
          "build": null,
          "person_classification": "Main",
          "dates_of_birth_used": [
              "December 1, 1988"
          ],
          "details": null,
          "warning_message": null,
          "suspects": null,
          "age_min": null,
          "hair": null,
          "title": "AHMED SAAD M ALMUTAIRI",
          "occupations": null,
          "@id": "https://api.fbi.gov/@wanted-person/126ac97fa13c4848b3ba66d03dbfd735"
      },
      {
          "eyes": "black",
          "sex": "Male",
          "age_max": null,
          "url": "https://www.fbi.gov/wanted/counterintelligence/hossein-ahmad-larijani",
          "ncic": "W421654733",
          "path": "/wanted/counterintelligence/hossein-ahmad-larijani",
          "locations": null,
          "weight_min": 175,
          "place_of_birth": "Tehran, Iran",
          "reward_min": 0,
          "subjects": [
              "Counterintelligence"
          ],
          "additional_information": null,
          "reward_max": 0,
          "languages": [
              "Persian (Farsi)",
              "English"
          ],
          "uid": "dbc4bf5166fd44409de586f4230c8d9e",
          "eyes_raw": "Black",
          "height_max": 68,
          "nationality": "Iranian",
          "age_range": null,
          "height_min": 68,
          "aliases": [
              "Hossein A. Larijani",
              "Hossein Larijani",
              "Mehrdad Ahmad Larijani",
              "Mehrdad Larijani"
          ],
          "reward_text": "The United States Department of State’s Transnational Organized Crime Rewards Program is offering a reward of up to $3 million for information leading to the arrest and/or conviction of Hossein Ahmad Larijani.",
          "possible_countries": null,
          "description": "Conspiracy to Defraud the United States by Dishonest Means; Smuggling; Illegal Exports and Attempted Illegal Exports in Violation of the International Emergency Economic Powers Act (IEEPA); Obstruction of Justice",
          "caution": "<p>Hossein Ahmad Larijani is wanted by the FBI, the U.S. Department of Homeland Security (Homeland Security Investigations) and the U.S. Department of Commerce (Office of Export Enforcement), for his alleged involvement in illegally procuring technology that originated in the United States and was later incorporated into Improvised Explosive Devices which targeted U.S. and coalition forces in Iraq from 2008 to 2010. Larijani executed this scheme with one Iranian company, three companies in Singapore, and four co-conspirators also in Singapore. Three co-conspirators were arrested and extradited to the U.S., pleaded guilty, served time in federal prison, and were deported back to Singapore. The remaining co-conspirator remains at large in Singapore.</p>\r\n<p> </p>\r\n<p>A federal arrest warrant was issued for Hossein Ahmad Larijani on September 15, 2010, in the United States District Court for the District of Columbia, Washington, D.C., after he was charged with conspiracy to defraud the United States by dishonest means; smuggling; illegal exports and attempted illegal exports in violation of the International Emergency Economic Powers Act (IEEPA); and obstruction of justice.</p>",
          "weight_max": 175,
          "legat_names": null,
          "race": "white",
          "modified": "2019-11-19T14:28:15+00:00",
          "publication": "2018-07-31T14:44:00",
          "weight": "Approximately 175 pounds",
          "status": "na",
          "possible_states": null,
          "scars_and_marks": null,
          "images": [
              {
                  "thumb": "https://www.fbi.gov/wanted/counterintelligence/hossein-ahmad-larijani/@@images/image/thumb",
                  "original": "https://www.fbi.gov/wanted/counterintelligence/hossein-ahmad-larijani/@@images/image",
                  "caption": "Photograph taken circa 2007",
                  "large": "https://www.fbi.gov/wanted/counterintelligence/hossein-ahmad-larijani/@@images/image/large"
              }
          ],
          "remarks": "<p>Larijani may travel to China, Singapore, Hong Kong, or Turkey.</p>",
          "files": [
              {
                  "name": "English",
                  "url": "https://www.fbi.gov/wanted/counterintelligence/hossein-ahmad-larijani/larijani-update-10-29-19.pdf"
              },
              {
                  "name": "به زبان فارسی",
                  "url": "https://www.fbi.gov/wanted/counterintelligence/hossein-ahmad-larijani/larijani_farsi_11-6-19.pdf/@@download/file/larijani_farsi_11-6-19.pdf"
              },
              {
                  "name": "بالعربیة",
                  "url": "https://www.fbi.gov/wanted/counterintelligence/hossein-ahmad-larijani/larijani_arabic_11-7-19.pdf/@@download/file/larijani_arabic_11-7-19.pdf"
              }
          ],
          "field_offices": [
              "minneapolis"
          ],
          "coordinates": [],
          "race_raw": "White",
          "hair_raw": "Black",
          "complexion": null,
          "build": null,
          "person_classification": "Main",
          "dates_of_birth_used": [
              "October 31, 1963",
              "August 31, 1963"
          ],
          "details": null,
          "warning_message": "SHOULD BE CONSIDERED AN INTERNATIONAL FLIGHT RISK",
          "suspects": null,
          "age_min": null,
          "hair": "black",
          "title": "HOSSEIN AHMAD LARIJANI",
          "occupations": [
              "Businessman"
          ],
          "@id": "https://api.fbi.gov/@wanted-person/dbc4bf5166fd44409de586f4230c8d9e"
      },
      {
          "age_range": null,
          "subjects": [
              "Additional Violent Crimes"
          ],
          "languages": null,
          "path": "/wanted/additional/zahidul-islam",
          "weight_min": 160,
          "details": null,
          "status": "na",
          "possible_states": [
              "US-NY",
              "US-PA"
          ],
          "eyes": "brown",
          "hair": "black",
          "legat_names": null,
          "eyes_raw": "Brown",
          "field_offices": [
              "philadelphia"
          ],
          "weight": "160 pounds",
          "age_min": null,
          "build": null,
          "person_classification": "Main",
          "remarks": "<p>Islam has ties to New York State and Montreal, Canada. He has a medium complexion and may wear glasses. He may be traveling with his wife, who is also a physician.</p>",
          "possible_countries": [
              "BGD",
              "CAN"
          ],
          "url": "https://www.fbi.gov/wanted/additional/zahidul-islam",
          "nationality": "Bangladeshi",
          "uid": "534b94b3179514e8bd779750a503c7c4",
          "warning_message": "SHOULD BE CONSIDERED ARMED AND DANGEROUS",
          "scars_and_marks": "None known",
          "race": "asian",
          "hair_raw": "Black",
          "modified": "2019-11-15T15:28:00+00:00",
          "title": "ZAHIDUL ISLAM",
          "images": [
              {
                  "large": "https://www.fbi.gov/wanted/additional/zahidul-islam/@@images/image/large",
                  "caption": null,
                  "original": "https://www.fbi.gov/wanted/additional/zahidul-islam/@@images/image",
                  "thumb": "https://www.fbi.gov/wanted/additional/zahidul-islam/@@images/image/thumb"
              }
          ],
          "complexion": null,
          "reward_text": null,
          "locations": null,
          "suspects": null,
          "additional_information": null,
          "caution": "<p>Zahidul Islam is wanted for the alleged sexual assault of a female patient at a major hospital in Philadelphia, Pennsylvania, on October 3, 1996. Authorities believe that while practicing medicine at this hospital, Islam gave the victim patient some medication to make her groggy and then forcibly raped her. The victim was recovering from surgery when she was assaulted in her hospital room. After state charges were filed against Islam, a federal warrant was issued for his arrest in the Eastern District of Pennsylvania in July of 1997.</p>",
          "reward_max": 0,
          "ncic": "W013165275",
          "aliases": null,
          "height_max": 65,
          "dates_of_birth_used": [
              "October 1, 1955"
          ],
          "height_min": 65,
          "files": [
              {
                  "url": "https://www.fbi.gov/wanted/additional/zahidul-islam/download.pdf",
                  "name": "English"
              },
              {
                  "url": "https://www.fbi.gov/wanted/additional/zahidul-islam/islambengali.pdf/@@download/file/islambengali.pdf",
                  "name": "বাংলাতে"
              }
          ],
          "occupations": [
              "Medical Doctor"
          ],
          "publication": "2010-08-31T16:35:00",
          "description": "Unlawful Flight to Avoid Prosecution - Involuntary Deviate Sexual Intercourse",
          "race_raw": "White (Central Asian)",
          "age_max": null,
          "coordinates": [],
          "place_of_birth": "Bangladesh",
          "reward_min": 0,
          "weight_max": 160,
          "sex": "Male",
          "@id": "https://api.fbi.gov/@wanted-person/534b94b3179514e8bd779750a503c7c4"
      },
      {
          "dates_of_birth_used": null,
          "images": [
              {
                  "caption": null,
                  "large": "https://www.fbi.gov/wanted/seeking-info/use-of-destructive-device/@@images/image/large",
                  "thumb": "https://www.fbi.gov/wanted/seeking-info/use-of-destructive-device/@@images/image/thumb",
                  "original": "https://www.fbi.gov/wanted/seeking-info/use-of-destructive-device/@@images/image"
              }
          ],
          "details": "<p>On July 17, 2019, at approximately 11:30pm, the individual seen in the photo was seen throwing a destructive device (molotov cocktail) at Police of Puerto Rico Agents during protests at La Fortaleza in San Juan, Puerto Rico. </p>\r\n<p> </p>",
          "warning_message": null,
          "build": null,
          "person_classification": "Main",
          "complexion": null,
          "race": null,
          "occupations": null,
          "suspects": null,
          "age_min": null,
          "hair": null,
          "legat_names": null,
          "modified": "2019-11-14T13:58:50+00:00",
          "status": "na",
          "publication": "2019-10-25T08:37:00",
          "weight": null,
          "caution": null,
          "possible_states": null,
          "scars_and_marks": null,
          "race_raw": null,
          "files": [
              {
                  "url": "https://www.fbi.gov/wanted/seeking-info/use-of-destructive-device/download.pdf",
                  "name": "English"
              }
          ],
          "field_offices": [
              "sanjuan"
          ],
          "nationality": null,
          "weight_min": null,
          "age_range": null,
          "uid": "0a24f87ee6f14a668debbfa8a58597e6",
          "eyes_raw": null,
          "height_max": null,
          "height_min": null,
          "aliases": null,
          "reward_text": "The FBI is offering a reward of up to $10,000 for information resulting in the identification, arrest, and conviction of the individual allegedly\r\nresponsible for throwing a destructive device (molotov cocktail) at Police of Puerto Rico Agents.",
          "description": "San Juan, Puerto Rico \r\nJuly 17, 2019",
          "title": "USE OF DESTRUCTIVE DEVICE",
          "possible_countries": null,
          "hair_raw": null,
          "remarks": null,
          "weight_max": null,
          "age_max": null,
          "url": "https://www.fbi.gov/wanted/seeking-info/use-of-destructive-device",
          "ncic": null,
          "eyes": null,
          "sex": null,
          "coordinates": [],
          "path": "/wanted/seeking-info/use-of-destructive-device",
          "place_of_birth": null,
          "reward_min": 0,
          "locations": null,
          "languages": null,
          "subjects": [
              "Seeking Information"
          ],
          "additional_information": null,
          "reward_max": 0,
          "@id": "https://api.fbi.gov/@wanted-person/0a24f87ee6f14a668debbfa8a58597e6"
      },
      {
          "age_range": null,
          "subjects": [
              "Seeking Information"
          ],
          "languages": null,
          "path": "/wanted/seeking-info/kenneth-knute-haugen",
          "weight_min": 190,
          "details": "<p>Kenneth Haugen was last seen on April 5, 2017, getting off a catamaran named the San Marlot, which was anchored at the Port of Luperon in the Dominican Republic. Haugen had recently sold the catamaran to another United States citizen. Haugen was reported missing on April 6, 2017, when his vehicle, a black Honda Civic, was found with the doors unlocked and the keys still in the vehicle near the beach in Luperon, less than a mile from where he lived. This area is also known as \"La Playita La Rusia\".  </p>\r\n<p> </p>",
          "status": "na",
          "possible_states": null,
          "eyes": "brown",
          "hair": "brown",
          "legat_names": [
              "americas-10"
          ],
          "eyes_raw": "Brown",
          "field_offices": [
              "miami"
          ],
          "weight": "190 pounds",
          "age_min": null,
          "build": null,
          "person_classification": "Victim",
          "remarks": null,
          "possible_countries": [
              "DOM"
          ],
          "url": "https://www.fbi.gov/wanted/seeking-info/kenneth-knute-haugen",
          "nationality": null,
          "uid": "ed4aaf8f0d5e41d9b06b56e8ec9f52b4",
          "warning_message": null,
          "scars_and_marks": null,
          "race": "white",
          "hair_raw": "Brown and Grey",
          "modified": "2019-11-14T13:55:26+00:00",
          "title": "KENNETH KNUTE HAUGEN",
          "images": [
              {
                  "large": "https://www.fbi.gov/wanted/seeking-info/kenneth-knute-haugen/@@images/image/large",
                  "caption": "Photo taken circa 2014",
                  "original": "https://www.fbi.gov/wanted/seeking-info/kenneth-knute-haugen/@@images/image",
                  "thumb": "https://www.fbi.gov/wanted/seeking-info/kenneth-knute-haugen/@@images/image/thumb"
              },
              {
                  "large": "https://www.fbi.gov/wanted/seeking-info/kenneth-knute-haugen/imagen-kenneth-knute-haugen-2019-02-28-13-17-2-20190228131914.jpg/@@images/image/large",
                  "caption": "",
                  "original": "https://www.fbi.gov/wanted/seeking-info/kenneth-knute-haugen/imagen-kenneth-knute-haugen-2019-02-28-13-17-2-20190228131914.jpg",
                  "thumb": "https://www.fbi.gov/wanted/seeking-info/kenneth-knute-haugen/imagen-kenneth-knute-haugen-2019-02-28-13-17-2-20190228131914.jpg/@@images/image/thumb"
              }
          ],
          "complexion": null,
          "reward_text": "The FBI is offering a reward of up to $10,000 USD for information leading directly to the arrest of the person(s) involved in the disappearance/murder of United States citizen Kenneth Knute Haugen.",
          "locations": null,
          "suspects": null,
          "additional_information": null,
          "caution": null,
          "reward_max": 0,
          "ncic": null,
          "aliases": [
              "Ken Haugen"
          ],
          "height_max": 69,
          "dates_of_birth_used": [
              "January 20, 1945"
          ],
          "height_min": 69,
          "files": [
              {
                  "url": "https://www.fbi.gov/wanted/seeking-info/kenneth-knute-haugen/download.pdf",
                  "name": "English"
              }
          ],
          "occupations": null,
          "publication": "2019-02-28T10:39:00",
          "description": "Missing Person/Victim\r\nPort of Luperon, Dominican Republic\r\nApril 5, 2017",
          "race_raw": "White",
          "age_max": null,
          "coordinates": [],
          "place_of_birth": null,
          "reward_min": 0,
          "weight_max": 190,
          "sex": "Male",
          "@id": "https://api.fbi.gov/@wanted-person/ed4aaf8f0d5e41d9b06b56e8ec9f52b4"
      },
      {
          "eyes": "brown",
          "sex": "Male",
          "age_max": 30,
          "url": "https://www.fbi.gov/wanted/seeking-info/attack-on-the-us-consulate-in-guadalajara",
          "ncic": null,
          "path": "/wanted/seeking-info/attack-on-the-us-consulate-in-guadalajara",
          "locations": null,
          "weight_min": null,
          "place_of_birth": null,
          "reward_min": 0,
          "subjects": [
              "Seeking Information"
          ],
          "additional_information": null,
          "reward_max": 0,
          "languages": null,
          "uid": "03a7c6ea1f4d4c3cb21d0224d481a2b8",
          "eyes_raw": "Brown",
          "height_max": 69,
          "nationality": null,
          "age_range": "late 20's to early 30's",
          "height_min": 65,
          "aliases": null,
          "reward_text": "The FBI is offering a  reward of up to $20,000 in exchange for information leading to the identification and arrest of the individual or group responsible for the attack at the U.S. Consulate in Guadalajara.",
          "possible_countries": [
              "MEX"
          ],
          "description": "November 30, 2018",
          "caution": null,
          "weight_max": null,
          "legat_names": [
              "americas-6"
          ],
          "race": null,
          "modified": "2019-11-14T13:53:26+00:00",
          "publication": "2018-12-21T12:23:00",
          "weight": null,
          "status": "na",
          "possible_states": null,
          "scars_and_marks": null,
          "images": [
              {
                  "thumb": "https://www.fbi.gov/wanted/seeking-info/attack-on-the-us-consulate-in-guadalajara/@@images/image/thumb",
                  "original": "https://www.fbi.gov/wanted/seeking-info/attack-on-the-us-consulate-in-guadalajara/@@images/image",
                  "caption": "Composite Sketch of Subject",
                  "large": "https://www.fbi.gov/wanted/seeking-info/attack-on-the-us-consulate-in-guadalajara/@@images/image/large"
              },
              {
                  "thumb": "https://www.fbi.gov/wanted/seeking-info/attack-on-the-us-consulate-in-guadalajara/still-image-subject-1-guadalajara.jpg/@@images/image/thumb",
                  "original": "https://www.fbi.gov/wanted/seeking-info/attack-on-the-us-consulate-in-guadalajara/still-image-subject-1-guadalajara.jpg",
                  "caption": "",
                  "large": "https://www.fbi.gov/wanted/seeking-info/attack-on-the-us-consulate-in-guadalajara/still-image-subject-1-guadalajara.jpg/@@images/image/large"
              }
          ],
          "remarks": null,
          "files": [
              {
                  "name": "English",
                  "url": "https://www.fbi.gov/wanted/seeking-info/attack-on-the-us-consulate-in-guadalajara/download.pdf"
              }
          ],
          "field_offices": null,
          "coordinates": [],
          "race_raw": null,
          "hair_raw": "Brown",
          "complexion": "Dark",
          "build": "Thin",
          "person_classification": "Main",
          "dates_of_birth_used": null,
          "details": "<p>The Federal Bureau of Investigation (FBI), in conjunction with other U.S. and Mexican law enforcement partners, is seeking the public’s assistance in learning the identity of the individual or group responsible for the grenade attack at the U.S. Consulate compound in Guadalajara, Jalisco, on November 30, 2018.</p>\r\n<p> </p>",
          "warning_message": null,
          "suspects": null,
          "age_min": 20,
          "hair": "brown",
          "title": "Attack on the U.S. Consulate in Guadalajara",
          "occupations": null,
          "@id": "https://api.fbi.gov/@wanted-person/03a7c6ea1f4d4c3cb21d0224d481a2b8"
      }
  ],
  "page": 22
}